kivy_gradient/__init__.py
KivyGradient-0.0.5.dist-info/METADATA
KivyGradient-0.0.5.dist-info/WHEEL
KivyGradient-0.0.5.dist-info/top_level.txt
KivyGradient-0.0.5.dist-info/RECORD
