Metadata-Version: 2.1
Name: KivyGradient
Version: 0.0.5
Summary: KivyGradient allows you to add a gradient color to your Kivy Widget
Home-page: https://github.com/kengoon/KivyGradient
Author: kengoon
Author-email: kengoon19@gmail.com
License: MIT
Requires-Dist: kivy
